example_maths/__init__.py
example_maths/bodmas.py
example_maths/data/function.txt
example_maths/tests/__init__.py
example_maths/tests/test_bodmas.py
example_maths/utils/__init__.py
example_maths/utils/json_logger.py
example_maths/utils/logging.conf
example_maths-0.1.1.data/scripts/local_test
example_maths-0.1.1.data/scripts/test_add
example_maths-0.1.1.dist-info/DESCRIPTION.rst
example_maths-0.1.1.dist-info/METADATA
example_maths-0.1.1.dist-info/RECORD
example_maths-0.1.1.dist-info/WHEEL
example_maths-0.1.1.dist-info/metadata.json
example_maths-0.1.1.dist-info/top_level.txt
