Metadata-Version: 2.0
Name: example-maths
Version: 0.1.1
Summary: example python package performing addition
Home-page: https://github.com/mwtmurphy/python-plugins
Author: mwtmurphy
Author-email: mwtmurphy@gmail.com
License: GPLv3+
Keywords: example plugin
Platform: UNKNOWN
Classifier: Development Status :: 2 - Pre-Alpha
Classifier: Natural Language :: English
Classifier: Programming Language :: Python :: 3
Classifier: Programming Language :: Python :: 3.6
Requires-Python: >=3
Requires-Dist: markdown
Requires-Dist: python-json-logger
